{
  "id": "pdf-pager",
  "title": "PDF Pager",
  "description": "Allows automatically loading of PDFs, and addition of specific page numbers in document links.",
  "version": "0.0.1",
  "library": "false",
  "compatibility": {
    "minimum": 10,
    "verified": 10.288
  },
  "authors": [
		{
			"name": "Farling",
			"url": "https://github.com/farling42",
			"email": "foundryvtt@amusingtime.uk",
			"discord": "Farling#9579",
			"ko-fi": "farling",
			"patreon": "amusingtime",
			"twitter": "@shambles42"
		}
  ],
  "relationships": {
    "requires": [
      {
        "id": "lib-wrapper",
        "type": "module",
        "manifest": "https://github.com/ruipin/fvtt-lib-wrapper/releases/latest/download/module.json",
        "compatibility": {}
      }      
    ]
  },
  "esmodules": [
    "scripts/pdf-actorbrowser.mjs",
    "scripts/pdf-actorsheet.mjs",
    "scripts/pdf-editable.mjs",
    "scripts/pdf-config.mjs",
    "scripts/pdf-linker.mjs",
    "scripts/pdf-menu.mjs",
    "scripts/pdf-pager.mjs",
    "scripts/pdf-migrate.mjs"
  ],
  "languages": [
    {
      "lang": "en",
      "name": "English",
      "path": "languages/en.json"
    }
  ],
  "url": "https://github.com/farling42/fvtt-pdf-pager",
  "manifest": "https://github.com/farling42/fvtt-pdf-pager/releases/latest/download/module.json",
  "download": "https://github.com/farling42/fvtt-pdf-pager/releases/latest/download/module.zip",
  "license": "LICENSE",
  "readme": "README.md"
}